simulation/__init__.py
simulation/dart/__init__.py
simulation/dart/config.py
simulation/dart/controller.py
simulation/dart/kinematics.py
simulation/dart/main.py
simulation/dart/robot.py
simulation/dart/test.py
simulation/dart/utils.py
simulation/matplotlib/__init__.py
simulation/matplotlib/gait.py
simulation/matplotlib/main.py
simulation/matplotlib/plotting.py
simulation/models/hrp4/meshes/CHEST_P.dae
simulation/models/hrp4/meshes/CHEST_R.dae
simulation/models/hrp4/meshes/CHEST_Y.dae
simulation/models/hrp4/meshes/ELBOW_P.dae
simulation/models/hrp4/meshes/F2.dae
simulation/models/hrp4/meshes/F2L.dae
simulation/models/hrp4/meshes/F2S.dae
simulation/models/hrp4/meshes/F3.dae
simulation/models/hrp4/meshes/F3L.dae
simulation/models/hrp4/meshes/F3S.dae
simulation/models/hrp4/meshes/HIP_Y.dae
simulation/models/hrp4/meshes/HRP4RBush_main.dae
simulation/models/hrp4/meshes/HRP4Rmain.dae
simulation/models/hrp4/meshes/KNEE_P.dae
simulation/models/hrp4/meshes/L_ANKLE_P.dae
simulation/models/hrp4/meshes/L_ANKLE_R.dae
simulation/models/hrp4/meshes/L_F1.dae
simulation/models/hrp4/meshes/L_FOOT.dae
simulation/models/hrp4/meshes/L_HIP_P.dae
simulation/models/hrp4/meshes/L_KNEE_P.dae
simulation/models/hrp4/meshes/L_SHOULDER_P.dae
simulation/models/hrp4/meshes/L_SHOULDER_R.dae
simulation/models/hrp4/meshes/L_THUMB.dae
simulation/models/hrp4/meshes/L_WRIST_R.dae
simulation/models/hrp4/meshes/L_WRIST_Y.dae
simulation/models/hrp4/meshes/NECK_P.dae
simulation/models/hrp4/meshes/NECK_R.dae
simulation/models/hrp4/meshes/NECK_Y.dae
simulation/models/hrp4/meshes/R_ANKLE_R.dae
simulation/models/hrp4/meshes/R_F1.dae
simulation/models/hrp4/meshes/R_FOOT.dae
simulation/models/hrp4/meshes/R_HIP_P.dae
simulation/models/hrp4/meshes/R_KNEE_P.dae
simulation/models/hrp4/meshes/R_SHOULDER_P.dae
simulation/models/hrp4/meshes/R_SHOULDER_R.dae
simulation/models/hrp4/meshes/R_THUMB.dae
simulation/models/hrp4/meshes/R_WRIST_P.dae
simulation/models/hrp4/meshes/R_WRIST_R.dae
ismpc_cpp-0.1.4.dist-info/METADATA
ismpc_cpp-0.1.4.dist-info/WHEEL
ismpc_cpp-0.1.4.dist-info/RECORD
