Metadata-Version: 2.4
Name: ismpc-cpp
Version: 0.1.4
Dynamic: Requires-Dist
Dynamic: Provides-Extra
Dynamic: Description
Dynamic: Description-Content-Type
Summary: Add a short description here
Author-email: neverorfrog <97flavio.maiorana@gmail.com>
Requires-Python: ==3.11
